ucms/__init__.py
ucms/ucms.py
ucms-1.0.0.dist-info/LICENSE
ucms-1.0.0.dist-info/METADATA
ucms-1.0.0.dist-info/WHEEL
ucms-1.0.0.dist-info/top_level.txt
ucms-1.0.0.dist-info/RECORD
