Metadata-Version: 2.1
Name: ucms
Version: 1.0.0
Summary: UCMS采集接口python推送库,用于python将采集内容推送到UCMS上
Home-page: https://github.com/dayudada/ucms_caiji_python
Author: dayudada
Author-email: dayudada@foxmail.com
License: MIT Licence
Keywords: ucms
Platform: any
Classifier: Programming Language :: Python :: 3
Classifier: License :: OSI Approved :: MIT License
Classifier: Operating System :: OS Independent
Requires-Python: >=3.6
Requires-Dist: requests
